    TRYCATCHBLOCK L0 L1 L2 java/lang/Throwable
    TRYCATCHBLOCK L3 L4 L2 java/lang/Throwable
   L5
    ALOAD 0
    INSTANCEOF org/jacoco/core/test/validation/java21/targets/RecordPatternsTarget$Point
    IFEQ L6
    ALOAD 0
    CHECKCAST org/jacoco/core/test/validation/java21/targets/RecordPatternsTarget$Point
    ASTORE 1
    ALOAD 1
   L0
    INVOKEVIRTUAL org/jacoco/core/test/validation/java21/targets/RecordPatternsTarget$Point.x ()I
   L1
    ISTORE 4
    ILOAD 4
    ISTORE 5
    ICONST_1
    IFEQ L6
    ILOAD 4
    ISTORE 2
   L7
    ALOAD 1
   L3
    INVOKEVIRTUAL org/jacoco/core/test/validation/java21/targets/RecordPatternsTarget$Point.y ()I
   L4
    ISTORE 4
    ILOAD 4
    ISTORE 5
    ICONST_1
    IFEQ L6
    ILOAD 4
    ISTORE 3
   L8
    ILOAD 2
    ILOAD 3
    IADD
    INVOKESTATIC org/jacoco/core/test/validation/targets/Stubs.nop (I)V
   L6
    GOTO L9
   L2
    ASTORE 1
    NEW java/lang/MatchException
    DUP
    ALOAD 1
    INVOKEVIRTUAL java/lang/Throwable.toString ()Ljava/lang/String;
    ALOAD 1
    INVOKESPECIAL java/lang/MatchException.<init> (Ljava/lang/String;Ljava/lang/Throwable;)V
    ATHROW
   L9
    RETURN
   L10
    LOCALVARIABLE x I L7 L6 2
    LOCALVARIABLE y I L8 L6 3
    LOCALVARIABLE o Ljava/lang/Object; L5 L10 0
    LINENUMBER 5 L5
    LINENUMBER 6 L8
    LINENUMBER 5 L2
    LINENUMBER 8 L9
    MAXSTACK = 4
    MAXLOCALS = 6
